pyrsc/__init__.py
pyrsc/src/util.py
pyrsc-1.2.0.dist-info/LICENSE
pyrsc-1.2.0.dist-info/METADATA
pyrsc-1.2.0.dist-info/WHEEL
pyrsc-1.2.0.dist-info/top_level.txt
pyrsc-1.2.0.dist-info/RECORD
