Metadata-Version: 2.1
Name: pyrsc
Version: 1.2.0
Summary: job handler in Python
Author: Moses Dastmard
License: UNKNOWN
Platform: UNKNOWN
License-File: LICENSE
